xenqu/XenquAPI.py
xenqu/_XenquBase.py
xenqu/__init__.py
xenqu/_utils.py
xenqu/models/Actor.py
xenqu/models/Address.py
xenqu/models/Contact.py
xenqu/models/Email.py
xenqu/models/Item.py
xenqu/models/OAuth2Token.py
xenqu/models/Phone.py
xenqu/models/Queue.py
xenqu/models/TrackingItem.py
xenqu/models/__init__.py
xenqu/routes/AccountRoutes.py
xenqu/routes/ContactRoutes.py
xenqu/routes/FileRoutes.py
xenqu/routes/FormRoutes.py
xenqu/routes/ReportRoutes.py
xenqu/routes/SearchRoutes.py
xenqu/routes/TrackingRoutes.py
xenqu/routes/__init__.py
xenqu/routes/Tracking/ItemRoutes.py
xenqu/routes/Tracking/QueueRoutes.py
xenqu/routes/Tracking/RecordRoutes.py
xenqu/routes/Tracking/TabRoutes.py
xenqu/routes/Tracking/__init__.py
xenqu_api-1.0.4.dist-info/METADATA
xenqu_api-1.0.4.dist-info/WHEEL
xenqu_api-1.0.4.dist-info/top_level.txt
xenqu_api-1.0.4.dist-info/RECORD
